odoo/addons/l10n_br_account_due_list/README.rst
odoo/addons/l10n_br_account_due_list/__init__.py
odoo/addons/l10n_br_account_due_list/__manifest__.py
odoo/addons/l10n_br_account_due_list/i18n/l10n_br_account_due_list.pot
odoo/addons/l10n_br_account_due_list/migrations/13.0.1.0.0/post-migration.py
odoo/addons/l10n_br_account_due_list/migrations/13.0.1.0.0/pre-migration.py
odoo/addons/l10n_br_account_due_list/models/__init__.py
odoo/addons/l10n_br_account_due_list/models/account_invoice.py
odoo/addons/l10n_br_account_due_list/readme/CONFIGURE.rst
odoo/addons/l10n_br_account_due_list/readme/CONTRIBUTORS.rst
odoo/addons/l10n_br_account_due_list/readme/DESCRIPTION.rst
odoo/addons/l10n_br_account_due_list/readme/HISTORY.rst
odoo/addons/l10n_br_account_due_list/readme/INSTALL.rst
odoo/addons/l10n_br_account_due_list/readme/ROADMAP.rst
odoo/addons/l10n_br_account_due_list/readme/USAGE.rst
odoo/addons/l10n_br_account_due_list/static/description/icon.png
odoo/addons/l10n_br_account_due_list/static/description/index.html
odoo/addons/l10n_br_account_due_list/static/img/l10n_br_account_due_list_payable.png
odoo/addons/l10n_br_account_due_list/static/img/l10n_br_account_due_list_receivable.png
odoo/addons/l10n_br_account_due_list/views/account_invoice_view.xml
odoo13_addon_l10n_br_account_due_list-13.0.1.0.1.dev4.dist-info/METADATA
odoo13_addon_l10n_br_account_due_list-13.0.1.0.1.dev4.dist-info/WHEEL
odoo13_addon_l10n_br_account_due_list-13.0.1.0.1.dev4.dist-info/top_level.txt
odoo13_addon_l10n_br_account_due_list-13.0.1.0.1.dev4.dist-info/RECORD
